Plotting/__init__.py
Plotting/sankey_chart.py
dsmodules101-0.0.4.dist-info/METADATA
dsmodules101-0.0.4.dist-info/WHEEL
dsmodules101-0.0.4.dist-info/top_level.txt
dsmodules101-0.0.4.dist-info/RECORD
