Metadata-Version: 2.1
Name: dsmodules101
Version: 0.0.4
Summary: A small package to help with some routine Data Science activities
Home-page: https://github.com/TanselArif-21/ds_modules_101
Author: Tansel Arif
Author-email: tanselarif21@gmail.com
License: MIT
Keywords: dsmodules,dsmodules101
Platform: UNKNOWN
Requires-Dist: numpy (>=1.19.2)
